[
  {
    "Id": "ef6b1049-4eef-4ba4-b54f-ca3277f43587",
    "Code": 1,
    "Name": "asdasda",
    "Nickname": null,
    "BirthDate": "2000-10-10T00:00:00",
    "PersonType": "pf",
    "Identity": "295.297.028-92",
    "Addresses": [
      {
        "Id": "ddea818f-0e0c-4d79-a923-807dd1c13ad0",
        "Type": null,
        "Street": null,
        "Number": null,
        "Complement": null,
        "District": null,
        "City": null,
        "State": null,
        "ZipCode": null,
        "Note": null
      }
    ],
    "Phones": [
      {
        "Id": "42422cab-207e-47ed-80f7-8ef05308e475",
        "Type": null,
        "Ddd": 0,
        "Number": 1122002222,
        "Note": null
      }
    ],
    "Emails": [
      {
        "Id": "479e6b97-3be5-468b-abb0-e6b8b3859abc",
        "Type": null,
        "Address": "asdas",
        "Note": null
      }
    ],
    "Note": "",
    "CreationDate": "0001-01-01T00:00:00",
    "CreationUserId": "00000000-0000-0000-0000-000000000000",
    "CreationUserName": null,
    "ChangeDate": null,
    "ChangeUserId": "00000000-0000-0000-0000-000000000000",
    "ChangeUserName": null,
    "cep": null
  },
  {
    "Id": "f55a2a0b-6c0e-4054-a54f-9e2f3dd64cf8",
    "Code": 2,
    "Name": "asdasdas",
    "Nickname": null,
    "BirthDate": "2000-10-10T00:00:00",
    "PersonType": "pf",
    "Identity": "295.297.028-92",
    "Addresses": [
      {
        "Id": "f89d0e90-49da-4688-bad0-9d7df10f5f33",
        "Type": null,
        "Street": null,
        "Number": null,
        "Complement": null,
        "District": null,
        "City": null,
        "State": null,
        "ZipCode": null,
        "Note": null
      }
    ],
    "Phones": [
      {
        "Id": "fc74ac94-44fd-41cd-a952-715d3d80f8fb",
        "Type": null,
        "Ddd": 0,
        "Number": 1112222,
        "Note": null
      }
    ],
    "Emails": [
      {
        "Id": "5b9ab639-c66c-44ae-8a44-564667462197",
        "Type": null,
        "Address": "",
        "Note": null
      }
    ],
    "Note": "",
    "CreationDate": "0001-01-01T00:00:00",
    "CreationUserId": "00000000-0000-0000-0000-000000000000",
    "CreationUserName": null,
    "ChangeDate": null,
    "ChangeUserId": "00000000-0000-0000-0000-000000000000",
    "ChangeUserName": null,
    "cep": null
  },
  {
    "Id": "d07a84a7-7f90-4a9e-ac09-4e411d8bdb44",
    "Code": 4,
    "Name": "Alex",
    "Nickname": null,
    "BirthDate": "2000-10-10T00:00:00",
    "PersonType": "pf",
    "Identity": "295.297.028-92",
    "Addresses": [
      {
        "Id": "16820abb-0351-4412-948b-7aac4327ca99",
        "Type": null,
        "Street": "Rua Jos\u00E9 Ces\u00E1rio Mendes",
        "Number": "122",
        "Complement": "",
        "District": "Vila No\u00EAmia",
        "City": "Mau\u00E1",
        "State": "SP",
        "ZipCode": "09370600",
        "Note": null
      }
    ],
    "Phones": [
      {
        "Id": "625d84a6-16c5-414c-a244-34feeccc4d60",
        "Type": null,
        "Ddd": 0,
        "Number": 11200000,
        "Note": null
      }
    ],
    "Emails": [
      {
        "Id": "535b9235-03f2-4ca0-adaf-69d48d972f0f",
        "Type": null,
        "Address": "",
        "Note": null
      }
    ],
    "Note": "",
    "CreationDate": "0001-01-01T00:00:00",
    "CreationUserId": "00000000-0000-0000-0000-000000000000",
    "CreationUserName": null,
    "ChangeDate": null,
    "ChangeUserId": "00000000-0000-0000-0000-000000000000",
    "ChangeUserName": null,
    "cep": null
  },
  {
    "Id": "3eb42f89-4604-44a0-aed0-f02a3d36070c",
    "Code": 5,
    "Name": "asdas",
    "Nickname": null,
    "BirthDate": "2000-10-10T00:00:00",
    "PersonType": "pf",
    "Identity": "295.297.028-92",
    "Addresses": [
      {
        "Id": "9f8faaf6-cb1b-43b4-86be-ff86ced140fd",
        "Type": null,
        "Street": "Rua Jos\u00E9 Ces\u00E1rio Mendes",
        "Number": "122",
        "Complement": "",
        "District": "Vila No\u00EAmia",
        "City": "Mau\u00E1",
        "State": "SP",
        "ZipCode": "09370600",
        "Note": null
      }
    ],
    "Phones": [
      {
        "Id": "0fbc465f-32a8-4667-8441-9c5fb2150ab0",
        "Type": null,
        "Ddd": 0,
        "Number": 119999000,
        "Note": null
      }
    ],
    "Emails": [
      {
        "Id": "9def1719-d861-482b-b0ee-dd4f6b5b6faa",
        "Type": null,
        "Address": "",
        "Note": null
      }
    ],
    "Note": "",
    "CreationDate": "0001-01-01T00:00:00",
    "CreationUserId": "00000000-0000-0000-0000-000000000000",
    "CreationUserName": null,
    "ChangeDate": null,
    "ChangeUserId": "00000000-0000-0000-0000-000000000000",
    "ChangeUserName": null,
    "cep": null
  },
  {
    "Id": "250bc664-d550-4abb-8973-72b7db0c52ae",
    "Code": 8,
    "Name": "asdasd",
    "Nickname": null,
    "BirthDate": "2000-10-10T00:00:00",
    "PersonType": "pf",
    "Identity": "295.297.028-92",
    "Addresses": [
      {
        "Id": "48f37390-7b73-4773-ba92-c65984027f2b",
        "Type": null,
        "Street": "Rua Jos\u00E9 Ces\u00E1rio Mendes",
        "Number": "1",
        "Complement": "",
        "District": "Vila No\u00EAmia",
        "City": "Mau\u00E1",
        "State": "SP",
        "ZipCode": "09370600",
        "Note": null
      }
    ],
    "Phones": [
      {
        "Id": "765cc28a-19eb-45ac-9f02-a8525a88dddf",
        "Type": null,
        "Ddd": 0,
        "Number": 11200000,
        "Note": null
      }
    ],
    "Emails": [
      {
        "Id": "e1e5c8e8-8db3-4a95-933d-4d3859b3a09d",
        "Type": null,
        "Address": "",
        "Note": null
      }
    ],
    "Note": "",
    "CreationDate": "0001-01-01T00:00:00",
    "CreationUserId": "00000000-0000-0000-0000-000000000000",
    "CreationUserName": null,
    "ChangeDate": null,
    "ChangeUserId": "00000000-0000-0000-0000-000000000000",
    "ChangeUserName": null,
    "cep": null
  },
  {
    "Id": "a12105c1-8cb9-4782-9007-ba7f93e206e5",
    "Code": 10,
    "Name": "Alex Costa",
    "Nickname": null,
    "BirthDate": "1981-04-29T00:00:00",
    "PersonType": "pf",
    "Identity": "295.297.028-92",
    "Addresses": [
      {
        "Id": "64b5439f-dc5b-4746-95c1-31071de2e4c1",
        "Type": null,
        "Street": "Rua Jos\u00E9 Ces\u00E1rio Mendes",
        "Number": "122",
        "Complement": "apto 715",
        "District": "Vila No\u00EAmia",
        "City": "Mau\u00E1",
        "State": "SP",
        "ZipCode": "09370600",
        "Note": null
      }
    ],
    "Phones": [
      {
        "Id": "11cd5afd-26bb-4e90-8a64-26e05cfc067f",
        "Type": null,
        "Ddd": 0,
        "Number": 11977521210,
        "Note": null
      }
    ],
    "Emails": [
      {
        "Id": "ebcf18e8-9e02-417d-b1bd-d391a9384899",
        "Type": null,
        "Address": "alexgcosta81@gmail.com",
        "Note": null
      }
    ],
    "Note": "",
    "CreationDate": "0001-01-01T00:00:00",
    "CreationUserId": "00000000-0000-0000-0000-000000000000",
    "CreationUserName": null,
    "ChangeDate": null,
    "ChangeUserId": "00000000-0000-0000-0000-000000000000",
    "ChangeUserName": null,
    "cep": null
  },
  {
    "Id": "65c21997-c715-49f0-9fcd-eb8809184f11",
    "Code": 11,
    "Name": "asdas",
    "Nickname": null,
    "BirthDate": "2000-10-10T00:00:00",
    "PersonType": "pf",
    "Identity": "295.297.028-92",
    "Addresses": [
      {
        "Id": "1c4a52e8-3cb4-4edb-a132-2cbc2db9d926",
        "Type": null,
        "Street": "Rua Jos\u00E9 Ces\u00E1rio Mendes",
        "Number": "122",
        "Complement": "",
        "District": "Vila No\u00EAmia",
        "City": "Mau\u00E1",
        "State": "SP",
        "ZipCode": "09370600",
        "Note": null
      }
    ],
    "Phones": [
      {
        "Id": "7419a5f7-4d72-466f-9ae1-d9578930d28a",
        "Type": null,
        "Ddd": 0,
        "Number": 11220000,
        "Note": null
      }
    ],
    "Emails": [
      {
        "Id": "861e6f30-f865-41c0-af1f-2d741063dff2",
        "Type": null,
        "Address": "",
        "Note": null
      }
    ],
    "Note": "",
    "CreationDate": "0001-01-01T00:00:00",
    "CreationUserId": "00000000-0000-0000-0000-000000000000",
    "CreationUserName": null,
    "ChangeDate": null,
    "ChangeUserId": "00000000-0000-0000-0000-000000000000",
    "ChangeUserName": null,
    "cep": null
  },
  {
    "Id": "7603f4b0-e9e4-43f7-8f0d-23de05bad3ea",
    "Code": 22,
    "Name": "asda",
    "Nickname": null,
    "BirthDate": "2000-10-10T00:00:00",
    "PersonType": "pf",
    "Identity": "295.297.028-92",
    "Addresses": [
      {
        "Id": "7e1d3435-7e59-459a-b714-302a55949894",
        "Type": null,
        "Street": "Rua Jos\u00E9 Ces\u00E1rio Mendes",
        "Number": "1",
        "Complement": "111",
        "District": "Vila No\u00EAmia",
        "City": "Mau\u00E1",
        "State": "SP",
        "ZipCode": "09370600",
        "Note": null
      }
    ],
    "Phones": [
      {
        "Id": "e28baac0-1701-4d6f-ba46-19a2710f967a",
        "Type": null,
        "Ddd": 0,
        "Number": 11222222,
        "Note": null
      }
    ],
    "Emails": [
      {
        "Id": "e6bb467b-5b73-4323-84cd-c0185bff7641",
        "Type": null,
        "Address": "sdaa",
        "Note": null
      }
    ],
    "Note": "s",
    "CreationDate": "0001-01-01T00:00:00",
    "CreationUserId": "00000000-0000-0000-0000-000000000000",
    "CreationUserName": null,
    "ChangeDate": null,
    "ChangeUserId": "00000000-0000-0000-0000-000000000000",
    "ChangeUserName": null,
    "cep": null
  },
  {
    "Id": "4289d6fc-0452-4e20-bd4a-c309cdf19c75",
    "Code": 3,
    "Name": "Alex",
    "Nickname": null,
    "BirthDate": "2000-10-10T00:00:00",
    "PersonType": "pf",
    "Identity": "295.297.028-92",
    "Addresses": [
      {
        "Id": "dbf592e3-0802-48dd-989d-2b5a6a61291a",
        "Type": null,
        "Street": "Rua Jos\u00E9 Ces\u00E1rio Mendes",
        "Number": "1",
        "Complement": "10",
        "District": "Vila No\u00EAmia",
        "City": "Mau\u00E1",
        "State": "SP",
        "ZipCode": "09370600",
        "Note": null
      }
    ],
    "Phones": [
      {
        "Id": "3a80c61b-9277-4f53-b6b0-2426dff2a04b",
        "Type": null,
        "Ddd": 0,
        "Number": 11222222,
        "Note": null
      }
    ],
    "Emails": [
      {
        "Id": "03afb3bc-649c-459c-b7a5-bba5cddbdb1d",
        "Type": null,
        "Address": "",
        "Note": null
      }
    ],
    "Note": "",
    "CreationDate": "0001-01-01T00:00:00",
    "CreationUserId": "00000000-0000-0000-0000-000000000000",
    "CreationUserName": null,
    "ChangeDate": null,
    "ChangeUserId": "00000000-0000-0000-0000-000000000000",
    "ChangeUserName": null,
    "cep": null
  },
  {
    "Id": "a0821927-b96d-4b6e-9cf9-44e1a4948257",
    "Code": 11,
    "Name": "asdasda",
    "Nickname": null,
    "BirthDate": "2000-10-10T00:00:00",
    "PersonType": "pf",
    "Identity": "295.297.028-92",
    "Addresses": [
      {
        "Id": "8cbf3c37-628d-4031-b8f6-1efb1da29043",
        "Type": null,
        "Street": "Rua Jos\u00E9 Ces\u00E1rio Mendes",
        "Number": "1",
        "Complement": "0",
        "District": "Vila No\u00EAmia",
        "City": "Mau\u00E1",
        "State": "SP",
        "ZipCode": "09370600",
        "Note": null
      }
    ],
    "Phones": [
      {
        "Id": "b09248e7-94e3-4092-afea-054474d62710",
        "Type": null,
        "Ddd": 0,
        "Number": 112222222,
        "Note": null
      }
    ],
    "Emails": [
      {
        "Id": "188d73aa-812b-4349-b084-8df53e3eb5e5",
        "Type": null,
        "Address": "",
        "Note": null
      }
    ],
    "Note": "",
    "CreationDate": "0001-01-01T00:00:00",
    "CreationUserId": "00000000-0000-0000-0000-000000000000",
    "CreationUserName": null,
    "ChangeDate": null,
    "ChangeUserId": "00000000-0000-0000-0000-000000000000",
    "ChangeUserName": null,
    "cep": null
  }
]